{
  "created_at": "2026-06-25T17:00:17",
  "file_type": "combined_auto_regulation_results",
  "description": "Zusammenfassung der automatischen Spannungsregelung aus mehreren Toleranz-Messungen. Enthält nur Regelungsdaten, keine vollständigen A/B-, Reflexions- oder Dissipationsdaten.",
  "source_files": [
    "konvention_regelung_toleranz_10p0pct_20260625_140304.json",
    "konvention_regelung_toleranz_5p0pct_20260625_141522.json",
    "konvention_regelung_toleranz_1p0pct_20260625_143912.json",
    "konvention_regelung_toleranz_0p0pct_20260625_145711.json"
  ],
  "runs": [
    {
      "source_file": "konvention_regelung_toleranz_10p0pct_20260625_140304.json",
      "created_at": "2026-06-25T14:03:04",
      "mode": "automatic",
      "purpose": "Referenzdaten für späteren Vergleich",
      "name": "regelung_toleranz",
      "target_amp_v": 0.1,
      "target_amp_uv": 100000.0,
      "tolerance": 0.1,
      "tolerance_percent": 10.0,
      "min_generator_voltage_v": 0.05,
      "max_generator_voltage_v": 1.0,
      "max_auto_steps": 15,
      "sweep_start_freq_hz": 350.0,
      "sweep_stop_freq_hz": 2050.0,
      "sweep_step_freq_hz": 50.0,
      "duration_s": 1.0,
      "frequencies": [
        {
          "frequency_hz": 350.0,
          "enabled": true,
          "target_amp_v": 0.1,
          "target_amp_uv": 100000.0,
          "tolerance": 0.1,
          "tolerance_percent": 10.0,
          "target_reached": true,
          "steps_count": 2,
          "amplitude_before_v": 0.0696525810053011,
          "amplitude_before_uv": 69652.5810053011,
          "amplitude_after_v": 0.09934704313328395,
          "amplitude_after_uv": 99347.04313328395,
          "relative_error_before": 0.30347418994698905,
          "relative_error_after": 0.006529568667160562,
          "generator_voltage_before_v": 0.05,
          "generator_voltage_after_v": 0.07178484885646487
        },
        {
          "frequency_hz": 400.0,
          "enabled": true,
          "target_amp_v": 0.1,
          "target_amp_uv": 100000.0,
          "tolerance": 0.1,
          "tolerance_percent": 10.0,
          "target_reached": false,
          "steps_count": 2,
          "amplitude_before_v": 0.2891961073978766,
          "amplitude_before_uv": 289196.1073978766,
          "amplitude_after_v": 0.2055501700556236,
          "amplitude_after_uv": 205550.1700556236,
          "relative_error_before": -1.8919610739787658,
          "relative_error_after": -1.0555017005562357,
          "generator_voltage_before_v": 0.07178484885646487,
          "generator_voltage_after_v": 0.05
        },
        {
          "frequency_hz": 450.0,
          "enabled": true,
          "target_amp_v": 0.1,
          "target_amp_uv": 100000.0,
          "tolerance": 0.1,
          "tolerance_percent": 10.0,
          "target_reached": false,
          "steps_count": 1,
          "amplitude_before_v": 0.17200711472137845,
          "amplitude_before_uv": 172007.11472137846,
          "amplitude_after_v": 0.17200711472137845,
          "amplitude_after_uv": 172007.11472137846,
          "relative_error_before": -0.7200711472137844,
          "relative_error_after": -0.7200711472137844,
          "generator_voltage_before_v": 0.05,
          "generator_voltage_after_v": 0.05
        },
        {
          "frequency_hz": 500.0,
          "enabled": true,
          "target_amp_v": 0.1,
          "target_amp_uv": 100000.0,
          "tolerance": 0.1,
          "tolerance_percent": 10.0,
          "target_reached": true,
          "steps_count": 2,
          "amplitude_before_v": 0.07237815093532556,
          "amplitude_before_uv": 72378.15093532555,
          "amplitude_after_v": 0.09872372117161522,
          "amplitude_after_uv": 98723.72117161522,
          "relative_error_before": 0.2762184906467445,
          "relative_error_after": 0.012762788283847831,
          "generator_voltage_before_v": 0.05,
          "generator_voltage_after_v": 0.06908162111517237
        },
        {
          "frequency_hz": 550.0,
          "enabled": true,
          "target_amp_v": 0.1,
          "target_amp_uv": 100000.0,
          "tolerance": 0.1,
          "tolerance_percent": 10.0,
          "target_reached": true,
          "steps_count": 2,
          "amplitude_before_v": 0.07194929457381004,
          "amplitude_before_uv": 71949.29457381004,
          "amplitude_after_v": 0.0989163785998087,
          "amplitude_after_uv": 98916.3785998087,
          "relative_error_before": 0.28050705426189965,
          "relative_error_after": 0.010836214001913036,
          "generator_voltage_before_v": 0.06908162111517237,
          "generator_voltage_after_v": 0.09601431330691369
        },
        {
          "frequency_hz": 600.0,
          "enabled": true,
          "target_amp_v": 0.1,
          "target_amp_uv": 100000.0,
          "tolerance": 0.1,
          "tolerance_percent": 10.0,
          "target_reached": true,
          "steps_count": 2,
          "amplitude_before_v": 0.1340258263947322,
          "amplitude_before_uv": 134025.8263947322,
          "amplitude_after_v": 0.10043746928634731,
          "amplitude_after_uv": 100437.4692863473,
          "relative_error_before": -0.340258263947322,
          "relative_error_after": -0.004374692863473029,
          "generator_voltage_before_v": 0.09601431330691369,
          "generator_voltage_after_v": 0.07163866538932312
        },
        {
          "frequency_hz": 650.0,
          "enabled": true,
          "target_amp_v": 0.1,
          "target_amp_uv": 100000.0,
          "tolerance": 0.1,
          "tolerance_percent": 10.0,
          "target_reached": false,
          "steps_count": 1,
          "amplitude_before_v": 0.324158896217272,
          "amplitude_before_uv": 324158.89621727203,
          "amplitude_after_v": 0.324158896217272,
          "amplitude_after_uv": 324158.89621727203,
          "relative_error_before": -2.24158896217272,
          "relative_error_after": -2.24158896217272,
          "generator_voltage_before_v": 0.05,
          "generator_voltage_after_v": 0.05
        },
        {
          "frequency_hz": 700.0,
          "enabled": true,
          "target_amp_v": 0.1,
          "target_amp_uv": 100000.0,
          "tolerance": 0.1,
          "tolerance_percent": 10.0,
          "target_reached": true,
          "steps_count": 2,
          "amplitude_before_v": 0.051218888847075,
          "amplitude_before_uv": 51218.888847074995,
          "amplitude_after_v": 0.09924752189272942,
          "amplitude_after_uv": 99247.52189272942,
          "relative_error_before": 0.48781111152925005,
          "relative_error_after": 0.007524781072705822,
          "generator_voltage_before_v": 0.05,
          "generator_voltage_after_v": 0.09762023566795748
        },
        {
          "frequency_hz": 750.0,
          "enabled": true,
          "target_amp_v": 0.1,
          "target_amp_uv": 100000.0,
          "tolerance": 0.1,
          "tolerance_percent": 10.0,
          "target_reached": true,
          "steps_count": 2,
          "amplitude_before_v": 0.06718385272549993,
          "amplitude_before_uv": 67183.85272549992,
          "amplitude_after_v": 0.09919170521912496,
          "amplitude_after_uv": 99191.70521912495,
          "relative_error_before": 0.3281614727450008,
          "relative_error_after": 0.008082947808750462,
          "generator_voltage_before_v": 0.09762023566795748,
          "generator_voltage_after_v": 0.1453031222626687
        },
        {
          "frequency_hz": 800.0,
          "enabled": true,
          "target_amp_v": 0.1,
          "target_amp_uv": 100000.0,
          "tolerance": 0.1,
          "tolerance_percent": 10.0,
          "target_reached": true,
          "steps_count": 2,
          "amplitude_before_v": 0.12022758002487786,
          "amplitude_before_uv": 120227.58002487787,
          "amplitude_after_v": 0.10036090402311594,
          "amplitude_after_uv": 100360.90402311595,
          "relative_error_before": -0.2022758002487786,
          "relative_error_after": -0.0036090402311593495,
          "generator_voltage_before_v": 0.1453031222626687,
          "generator_voltage_after_v": 0.12085673040361751
        },
        {
          "frequency_hz": 850.0,
          "enabled": true,
          "target_amp_v": 0.1,
          "target_amp_uv": 100000.0,
          "tolerance": 0.1,
          "tolerance_percent": 10.0,
          "target_reached": false,
          "steps_count": 2,
          "amplitude_before_v": 0.31778641149922954,
          "amplitude_before_uv": 317786.41149922955,
          "amplitude_after_v": 0.13526403103519413,
          "amplitude_after_uv": 135264.03103519414,
          "relative_error_before": -2.1778641149922953,
          "relative_error_after": -0.35264031035194127,
          "generator_voltage_before_v": 0.12085673040361751,
          "generator_voltage_after_v": 0.05
        },
        {
          "frequency_hz": 900.0,
          "enabled": true,
          "target_amp_v": 0.1,
          "target_amp_uv": 100000.0,
          "tolerance": 0.1,
          "tolerance_percent": 10.0,
          "target_reached": true,
          "steps_count": 2,
          "amplitude_before_v": 0.07885905192653807,
          "amplitude_before_uv": 78859.05192653807,
          "amplitude_after_v": 0.09979428970183268,
          "amplitude_after_uv": 99794.28970183268,
          "relative_error_before": 0.21140948073461938,
          "relative_error_after": 0.00205710298167322,
          "generator_voltage_before_v": 0.05,
          "generator_voltage_after_v": 0.06340426213333626
        },
        {
          "frequency_hz": 950.0,
          "enabled": true,
          "target_amp_v": 0.1,
          "target_amp_uv": 100000.0,
          "tolerance": 0.1,
          "tolerance_percent": 10.0,
          "target_reached": true,
          "steps_count": 2,
          "amplitude_before_v": 0.05085140189999947,
          "amplitude_before_uv": 50851.401899999466,
          "amplitude_after_v": 0.09741862824780217,
          "amplitude_after_uv": 97418.62824780217,
          "relative_error_before": 0.49148598100000535,
          "relative_error_after": 0.025813717521978308,
          "generator_voltage_before_v": 0.06340426213333626,
          "generator_voltage_after_v": 0.1246853769278091
        },
        {
          "frequency_hz": 1000.0,
          "enabled": true,
          "target_amp_v": 0.1,
          "target_amp_uv": 100000.0,
          "tolerance": 0.1,
          "tolerance_percent": 10.0,
          "target_reached": true,
          "steps_count": 2,
          "amplitude_before_v": 0.08798093898163564,
          "amplitude_before_uv": 87980.93898163564,
          "amplitude_after_v": 0.09889310169642503,
          "amplitude_after_uv": 98893.10169642503,
          "relative_error_before": 0.12019061018364363,
          "relative_error_after": 0.011068983035749796,
          "generator_voltage_before_v": 0.1246853769278091,
          "generator_voltage_after_v": 0.1417186249312679
        },
        {
          "frequency_hz": 1050.0,
          "enabled": true,
          "target_amp_v": 0.1,
          "target_amp_uv": 100000.0,
          "tolerance": 0.1,
          "tolerance_percent": 10.0,
          "target_reached": true,
          "steps_count": 2,
          "amplitude_before_v": 0.1384735117798895,
          "amplitude_before_uv": 138473.5117798895,
          "amplitude_after_v": 0.10290555391590722,
          "amplitude_after_uv": 102905.55391590722,
          "relative_error_before": -0.384735117798895,
          "relative_error_after": -0.029055539159072163,
          "generator_voltage_before_v": 0.1417186249312679,
          "generator_voltage_after_v": 0.1023434901799221
        },
        {
          "frequency_hz": 1100.0,
          "enabled": true,
          "target_amp_v": 0.1,
          "target_amp_uv": 100000.0,
          "tolerance": 0.1,
          "tolerance_percent": 10.0,
          "target_reached": false,
          "steps_count": 1,
          "amplitude_before_v": 0.22972835932844865,
          "amplitude_before_uv": 229728.35932844866,
          "amplitude_after_v": 0.22972835932844865,
          "amplitude_after_uv": 229728.35932844866,
          "relative_error_before": -1.2972835932844864,
          "relative_error_after": -1.2972835932844864,
          "generator_voltage_before_v": 0.05,
          "generator_voltage_after_v": 0.05
        },
        {
          "frequency_hz": 1150.0,
          "enabled": true,
          "target_amp_v": 0.1,
          "target_amp_uv": 100000.0,
          "tolerance": 0.1,
          "tolerance_percent": 10.0,
          "target_reached": true,
          "steps_count": 2,
          "amplitude_before_v": 0.02323942078552796,
          "amplitude_before_uv": 23239.42078552796,
          "amplitude_after_v": 0.09162079109878797,
          "amplitude_after_uv": 91620.79109878797,
          "relative_error_before": 0.7676057921447205,
          "relative_error_after": 0.08379208901212035,
          "generator_voltage_before_v": 0.05,
          "generator_voltage_after_v": 0.21515166173584382
        },
        {
          "frequency_hz": 1200.0,
          "enabled": true,
          "target_amp_v": 0.1,
          "target_amp_uv": 100000.0,
          "tolerance": 0.1,
          "tolerance_percent": 10.0,
          "target_reached": true,
          "steps_count": 4,
          "amplitude_before_v": 0.0386330382622651,
          "amplitude_before_uv": 38633.0382622651,
          "amplitude_after_v": 0.10125204909386959,
          "amplitude_after_uv": 101252.04909386959,
          "relative_error_before": 0.613669617377349,
          "relative_error_after": -0.012520490938695839,
          "generator_voltage_before_v": 0.21515166173584382,
          "generator_voltage_after_v": 1.0
        },
        {
          "frequency_hz": 1250.0,
          "enabled": true,
          "target_amp_v": 0.1,
          "target_amp_uv": 100000.0,
          "tolerance": 0.1,
          "tolerance_percent": 10.0,
          "target_reached": false,
          "steps_count": 1,
          "amplitude_before_v": 0.049107291395083366,
          "amplitude_before_uv": 49107.29139508337,
          "amplitude_after_v": 0.049107291395083366,
          "amplitude_after_uv": 49107.29139508337,
          "relative_error_before": 0.5089270860491664,
          "relative_error_after": 0.5089270860491664,
          "generator_voltage_before_v": 1.0,
          "generator_voltage_after_v": 1.0
        },
        {
          "frequency_hz": 1300.0,
          "enabled": true,
          "target_amp_v": 0.1,
          "target_amp_uv": 100000.0,
          "tolerance": 0.1,
          "tolerance_percent": 10.0,
          "target_reached": true,
          "steps_count": 3,
          "amplitude_before_v": 0.16993392484018832,
          "amplitude_before_uv": 169933.92484018832,
          "amplitude_after_v": 0.1010970752365393,
          "amplitude_after_uv": 101097.0752365393,
          "relative_error_before": -0.6993392484018831,
          "relative_error_after": -0.01097075236539291,
          "generator_voltage_before_v": 1.0,
          "generator_voltage_after_v": 0.4140119723126162
        },
        {
          "frequency_hz": 1350.0,
          "enabled": true,
          "target_amp_v": 0.1,
          "target_amp_uv": 100000.0,
          "tolerance": 0.1,
          "tolerance_percent": 10.0,
          "target_reached": true,
          "steps_count": 2,
          "amplitude_before_v": 0.13508432304173917,
          "amplitude_before_uv": 135084.32304173918,
          "amplitude_after_v": 0.10577377532690724,
          "amplitude_after_uv": 105773.77532690724,
          "relative_error_before": -0.3508432304173917,
          "relative_error_after": -0.05773775326907232,
          "generator_voltage_before_v": 0.4140119723126162,
          "generator_voltage_after_v": 0.30648410043971386
        },
        {
          "frequency_hz": 1400.0,
          "enabled": true,
          "target_amp_v": 0.1,
          "target_amp_uv": 100000.0,
          "tolerance": 0.1,
          "tolerance_percent": 10.0,
          "target_reached": true,
          "steps_count": 1,
          "amplitude_before_v": 0.09187727553375145,
          "amplitude_before_uv": 91877.27553375145,
          "amplitude_after_v": 0.09187727553375145,
          "amplitude_after_uv": 91877.27553375145,
          "relative_error_before": 0.08122724466248551,
          "relative_error_after": 0.08122724466248551,
          "generator_voltage_before_v": 0.30648410043971386,
          "generator_voltage_after_v": 0.30648410043971386
        },
        {
          "frequency_hz": 1450.0,
          "enabled": true,
          "target_amp_v": 0.1,
          "target_amp_uv": 100000.0,
          "tolerance": 0.1,
          "tolerance_percent": 10.0,
          "target_reached": true,
          "steps_count": 2,
          "amplitude_before_v": 0.12052093978254527,
          "amplitude_before_uv": 120520.93978254528,
          "amplitude_after_v": 0.10233848824584285,
          "amplitude_after_uv": 102338.48824584285,
          "relative_error_before": -0.20520939782545267,
          "relative_error_after": -0.023384882458428458,
          "generator_voltage_before_v": 0.30648410043971386,
          "generator_voltage_after_v": 0.25429946114771185
        },
        {
          "frequency_hz": 1500.0,
          "enabled": true,
          "target_amp_v": 0.1,
          "target_amp_uv": 100000.0,
          "tolerance": 0.1,
          "tolerance_percent": 10.0,
          "target_reached": true,
          "steps_count": 2,
          "amplitude_before_v": 0.2063189430279142,
          "amplitude_before_uv": 206318.9430279142,
          "amplitude_after_v": 0.0973998663150526,
          "amplitude_after_uv": 97399.8663150526,
          "relative_error_before": -1.0631894302791418,
          "relative_error_after": 0.026001336849474088,
          "generator_voltage_before_v": 0.25429946114771185,
          "generator_voltage_after_v": 0.12325550791139596
        },
        {
          "frequency_hz": 1550.0,
          "enabled": true,
          "target_amp_v": 0.1,
          "target_amp_uv": 100000.0,
          "tolerance": 0.1,
          "tolerance_percent": 10.0,
          "target_reached": true,
          "steps_count": 2,
          "amplitude_before_v": 0.23934672658095263,
          "amplitude_before_uv": 239346.72658095264,
          "amplitude_after_v": 0.09678904824743292,
          "amplitude_after_uv": 96789.04824743292,
          "relative_error_before": -1.3934672658095262,
          "relative_error_after": 0.032109517525670817,
          "generator_voltage_before_v": 0.12325550791139596,
          "generator_voltage_after_v": 0.051496634055361985
        },
        {
          "frequency_hz": 1600.0,
          "enabled": true,
          "target_amp_v": 0.1,
          "target_amp_uv": 100000.0,
          "tolerance": 0.1,
          "tolerance_percent": 10.0,
          "target_reached": true,
          "steps_count": 3,
          "amplitude_before_v": 0.023458784411921087,
          "amplitude_before_uv": 23458.784411921086,
          "amplitude_after_v": 0.09930082804662325,
          "amplitude_after_uv": 99300.82804662325,
          "relative_error_before": 0.7654121558807891,
          "relative_error_after": 0.00699171953376751,
          "generator_voltage_before_v": 0.051496634055361985,
          "generator_voltage_after_v": 0.19839372702109873
        },
        {
          "frequency_hz": 1650.0,
          "enabled": true,
          "target_amp_v": 0.1,
          "target_amp_uv": 100000.0,
          "tolerance": 0.1,
          "tolerance_percent": 10.0,
          "target_reached": true,
          "steps_count": 2,
          "amplitude_before_v": 0.0747072454697929,
          "amplitude_before_uv": 74707.2454697929,
          "amplitude_after_v": 0.10083113239147849,
          "amplitude_after_uv": 100831.13239147849,
          "relative_error_before": 0.252927545302071,
          "relative_error_after": -0.008311323914784868,
          "generator_voltage_before_v": 0.19839372702109873,
          "generator_voltage_after_v": 0.2655615606904708
        },
        {
          "frequency_hz": 1700.0,
          "enabled": true,
          "target_amp_v": 0.1,
          "target_amp_uv": 100000.0,
          "tolerance": 0.1,
          "tolerance_percent": 10.0,
          "target_reached": true,
          "steps_count": 2,
          "amplitude_before_v": 0.13252114208002594,
          "amplitude_before_uv": 132521.14208002595,
          "amplitude_after_v": 0.0999105323496215,
          "amplitude_after_uv": 99910.5323496215,
          "relative_error_before": -0.32521142080025933,
          "relative_error_after": 0.0008946765037851079,
          "generator_voltage_before_v": 0.2655615606904708,
          "generator_voltage_after_v": 0.20039184429009935
        },
        {
          "frequency_hz": 1750.0,
          "enabled": true,
          "target_amp_v": 0.1,
          "target_amp_uv": 100000.0,
          "tolerance": 0.1,
          "tolerance_percent": 10.0,
          "target_reached": false,
          "steps_count": 1,
          "amplitude_before_v": 0.12906347286581285,
          "amplitude_before_uv": 129063.47286581284,
          "amplitude_after_v": 0.12906347286581285,
          "amplitude_after_uv": 129063.47286581284,
          "relative_error_before": -0.29063472865812845,
          "relative_error_after": -0.29063472865812845,
          "generator_voltage_before_v": 0.05,
          "generator_voltage_after_v": 0.05
        },
        {
          "frequency_hz": 1800.0,
          "enabled": true,
          "target_amp_v": 0.1,
          "target_amp_uv": 100000.0,
          "tolerance": 0.1,
          "tolerance_percent": 10.0,
          "target_reached": true,
          "steps_count": 2,
          "amplitude_before_v": 0.034569680151934394,
          "amplitude_before_uv": 34569.68015193439,
          "amplitude_after_v": 0.09586622829177158,
          "amplitude_after_uv": 95866.22829177158,
          "relative_error_before": 0.654303198480656,
          "relative_error_after": 0.04133771708228429,
          "generator_voltage_before_v": 0.05,
          "generator_voltage_after_v": 0.14463541397780574
        },
        {
          "frequency_hz": 1850.0,
          "enabled": true,
          "target_amp_v": 0.1,
          "target_amp_uv": 100000.0,
          "tolerance": 0.1,
          "tolerance_percent": 10.0,
          "target_reached": true,
          "steps_count": 2,
          "amplitude_before_v": 0.058034874372155786,
          "amplitude_before_uv": 58034.874372155784,
          "amplitude_after_v": 0.09727672259884979,
          "amplitude_after_uv": 97276.72259884978,
          "relative_error_before": 0.4196512562784422,
          "relative_error_after": 0.027232774011502203,
          "generator_voltage_before_v": 0.14463541397780574,
          "generator_voltage_after_v": 0.24922155090372233
        },
        {
          "frequency_hz": 1900.0,
          "enabled": true,
          "target_amp_v": 0.1,
          "target_amp_uv": 100000.0,
          "tolerance": 0.1,
          "tolerance_percent": 10.0,
          "target_reached": true,
          "steps_count": 2,
          "amplitude_before_v": 0.11022242422031293,
          "amplitude_before_uv": 110222.42422031294,
          "amplitude_after_v": 0.10011577696527381,
          "amplitude_after_uv": 100115.7769652738,
          "relative_error_before": -0.10222424220312928,
          "relative_error_after": -0.0011577696527380332,
          "generator_voltage_before_v": 0.24922155090372233,
          "generator_voltage_after_v": 0.22610784753138474
        },
        {
          "frequency_hz": 1950.0,
          "enabled": true,
          "target_amp_v": 0.1,
          "target_amp_uv": 100000.0,
          "tolerance": 0.1,
          "tolerance_percent": 10.0,
          "target_reached": true,
          "steps_count": 2,
          "amplitude_before_v": 0.27985236957090126,
          "amplitude_before_uv": 279852.36957090127,
          "amplitude_after_v": 0.10238001770184088,
          "amplitude_after_uv": 102380.01770184089,
          "relative_error_before": -1.7985236957090125,
          "relative_error_after": -0.023800177018408752,
          "generator_voltage_before_v": 0.22610784753138474,
          "generator_voltage_after_v": 0.08079540218911452
        },
        {
          "frequency_hz": 2000.0,
          "enabled": true,
          "target_amp_v": 0.1,
          "target_amp_uv": 100000.0,
          "tolerance": 0.1,
          "tolerance_percent": 10.0,
          "target_reached": true,
          "steps_count": 2,
          "amplitude_before_v": 0.07554167195972818,
          "amplitude_before_uv": 75541.67195972818,
          "amplitude_after_v": 0.0997865902603428,
          "amplitude_after_uv": 99786.5902603428,
          "relative_error_before": 0.2445832804027183,
          "relative_error_after": 0.002134097396572082,
          "generator_voltage_before_v": 0.08079540218911452,
          "generator_voltage_after_v": 0.10695474443710697
        }
      ]
    },
    {
      "source_file": "konvention_regelung_toleranz_5p0pct_20260625_141522.json",
      "created_at": "2026-06-25T14:15:22",
      "mode": "automatic",
      "purpose": "Referenzdaten für späteren Vergleich",
      "name": "regelung_toleranz",
      "target_amp_v": 0.15,
      "target_amp_uv": 150000.0,
      "tolerance": 0.05,
      "tolerance_percent": 5.0,
      "min_generator_voltage_v": 0.05,
      "max_generator_voltage_v": 1.0,
      "max_auto_steps": 15,
      "sweep_start_freq_hz": 350.0,
      "sweep_stop_freq_hz": 2050.0,
      "sweep_step_freq_hz": 50.0,
      "duration_s": 1.0,
      "frequencies": [
        {
          "frequency_hz": 350.0,
          "enabled": true,
          "target_amp_v": 0.15,
          "target_amp_uv": 150000.0,
          "tolerance": 0.05,
          "tolerance_percent": 5.0,
          "target_reached": true,
          "steps_count": 2,
          "amplitude_before_v": 0.06964645799846829,
          "amplitude_before_uv": 69646.4579984683,
          "amplitude_after_v": 0.1470080860784298,
          "amplitude_after_uv": 147008.0860784298,
          "relative_error_before": 0.5356902800102114,
          "relative_error_after": 0.019946092810467962,
          "generator_voltage_before_v": 0.05,
          "generator_voltage_after_v": 0.1076867397916669
        },
        {
          "frequency_hz": 400.0,
          "enabled": true,
          "target_amp_v": 0.15,
          "target_amp_uv": 150000.0,
          "tolerance": 0.05,
          "tolerance_percent": 5.0,
          "target_reached": false,
          "steps_count": 1,
          "amplitude_before_v": 0.20328662903711753,
          "amplitude_before_uv": 203286.62903711753,
          "amplitude_after_v": 0.20328662903711753,
          "amplitude_after_uv": 203286.62903711753,
          "relative_error_before": -0.3552441935807836,
          "relative_error_after": -0.3552441935807836,
          "generator_voltage_before_v": 0.05,
          "generator_voltage_after_v": 0.05
        },
        {
          "frequency_hz": 450.0,
          "enabled": true,
          "target_amp_v": 0.15,
          "target_amp_uv": 150000.0,
          "tolerance": 0.05,
          "tolerance_percent": 5.0,
          "target_reached": false,
          "steps_count": 1,
          "amplitude_before_v": 0.17219762891812881,
          "amplitude_before_uv": 172197.62891812882,
          "amplitude_after_v": 0.17219762891812881,
          "amplitude_after_uv": 172197.62891812882,
          "relative_error_before": -0.14798419278752548,
          "relative_error_after": -0.14798419278752548,
          "generator_voltage_before_v": 0.05,
          "generator_voltage_after_v": 0.05
        },
        {
          "frequency_hz": 500.0,
          "enabled": true,
          "target_amp_v": 0.15,
          "target_amp_uv": 150000.0,
          "tolerance": 0.05,
          "tolerance_percent": 5.0,
          "target_reached": true,
          "steps_count": 2,
          "amplitude_before_v": 0.07200145598876262,
          "amplitude_before_uv": 72001.45598876262,
          "amplitude_after_v": 0.14400897627490764,
          "amplitude_after_uv": 144008.97627490765,
          "relative_error_before": 0.5199902934082492,
          "relative_error_after": 0.0399401581672824,
          "generator_voltage_before_v": 0.05,
          "generator_voltage_after_v": 0.10416456024259249
        },
        {
          "frequency_hz": 550.0,
          "enabled": true,
          "target_amp_v": 0.15,
          "target_amp_uv": 150000.0,
          "tolerance": 0.05,
          "tolerance_percent": 5.0,
          "target_reached": true,
          "steps_count": 2,
          "amplitude_before_v": 0.10606594577977788,
          "amplitude_before_uv": 106065.94577977787,
          "amplitude_after_v": 0.1471381753498331,
          "amplitude_after_uv": 147138.1753498331,
          "relative_error_before": 0.2928936948014808,
          "relative_error_after": 0.019078831001112705,
          "generator_voltage_before_v": 0.10416456024259249,
          "generator_voltage_after_v": 0.14731103297454878
        },
        {
          "frequency_hz": 600.0,
          "enabled": true,
          "target_amp_v": 0.15,
          "target_amp_uv": 150000.0,
          "tolerance": 0.05,
          "tolerance_percent": 5.0,
          "target_reached": true,
          "steps_count": 2,
          "amplitude_before_v": 0.20099055652249997,
          "amplitude_before_uv": 200990.55652249997,
          "amplitude_after_v": 0.15105132937714286,
          "amplitude_after_uv": 151051.32937714286,
          "relative_error_before": -0.3399370434833332,
          "relative_error_after": -0.007008862514285749,
          "generator_voltage_before_v": 0.14731103297454878,
          "generator_voltage_after_v": 0.10993877189249315
        },
        {
          "frequency_hz": 650.0,
          "enabled": true,
          "target_amp_v": 0.15,
          "target_amp_uv": 150000.0,
          "tolerance": 0.05,
          "tolerance_percent": 5.0,
          "target_reached": false,
          "steps_count": 1,
          "amplitude_before_v": 0.3240076717254402,
          "amplitude_before_uv": 324007.6717254402,
          "amplitude_after_v": 0.3240076717254402,
          "amplitude_after_uv": 324007.6717254402,
          "relative_error_before": -1.160051144836268,
          "relative_error_after": -1.160051144836268,
          "generator_voltage_before_v": 0.05,
          "generator_voltage_after_v": 0.05
        },
        {
          "frequency_hz": 700.0,
          "enabled": true,
          "target_amp_v": 0.15,
          "target_amp_uv": 150000.0,
          "tolerance": 0.05,
          "tolerance_percent": 5.0,
          "target_reached": true,
          "steps_count": 2,
          "amplitude_before_v": 0.051035207190510974,
          "amplitude_before_uv": 51035.20719051098,
          "amplitude_after_v": 0.14766465270623946,
          "amplitude_after_uv": 147664.65270623946,
          "relative_error_before": 0.6597652853965935,
          "relative_error_after": 0.015568981958403543,
          "generator_voltage_before_v": 0.05,
          "generator_voltage_after_v": 0.14695737340412962
        },
        {
          "frequency_hz": 750.0,
          "enabled": true,
          "target_amp_v": 0.15,
          "target_amp_uv": 150000.0,
          "tolerance": 0.05,
          "tolerance_percent": 5.0,
          "target_reached": true,
          "steps_count": 2,
          "amplitude_before_v": 0.0996711844588701,
          "amplitude_before_uv": 99671.1844588701,
          "amplitude_after_v": 0.14788020607832023,
          "amplitude_after_uv": 147880.20607832022,
          "relative_error_before": 0.33552543694086595,
          "relative_error_after": 0.014131959477865127,
          "generator_voltage_before_v": 0.14695737340412962,
          "generator_voltage_after_v": 0.22116327933771773
        },
        {
          "frequency_hz": 800.0,
          "enabled": true,
          "target_amp_v": 0.15,
          "target_amp_uv": 150000.0,
          "tolerance": 0.05,
          "tolerance_percent": 5.0,
          "target_reached": true,
          "steps_count": 2,
          "amplitude_before_v": 0.1783469709226053,
          "amplitude_before_uv": 178346.97092260528,
          "amplitude_after_v": 0.15120470673167763,
          "amplitude_after_uv": 151204.70673167764,
          "relative_error_before": -0.18897980615070198,
          "relative_error_after": -0.008031378211184234,
          "generator_voltage_before_v": 0.22116327933771773,
          "generator_voltage_after_v": 0.18601096351038063
        },
        {
          "frequency_hz": 850.0,
          "enabled": true,
          "target_amp_v": 0.15,
          "target_amp_uv": 150000.0,
          "tolerance": 0.05,
          "tolerance_percent": 5.0,
          "target_reached": true,
          "steps_count": 2,
          "amplitude_before_v": 0.1332900188372924,
          "amplitude_before_uv": 133290.01883729242,
          "amplitude_after_v": 0.1499557289173651,
          "amplitude_after_uv": 149955.7289173651,
          "relative_error_before": 0.11139987441805055,
          "relative_error_after": 0.0002951405508992237,
          "generator_voltage_before_v": 0.05,
          "generator_voltage_after_v": 0.05626827924076601
        },
        {
          "frequency_hz": 900.0,
          "enabled": true,
          "target_amp_v": 0.15,
          "target_amp_uv": 150000.0,
          "tolerance": 0.05,
          "tolerance_percent": 5.0,
          "target_reached": true,
          "steps_count": 2,
          "amplitude_before_v": 0.08902156025432063,
          "amplitude_before_uv": 89021.56025432063,
          "amplitude_after_v": 0.14887007424498466,
          "amplitude_after_uv": 148870.07424498466,
          "relative_error_before": 0.4065229316378624,
          "relative_error_after": 0.007532838366768879,
          "generator_voltage_before_v": 0.05626827924076601,
          "generator_voltage_after_v": 0.0948112104742676
        },
        {
          "frequency_hz": 950.0,
          "enabled": true,
          "target_amp_v": 0.15,
          "target_amp_uv": 150000.0,
          "tolerance": 0.05,
          "tolerance_percent": 5.0,
          "target_reached": true,
          "steps_count": 2,
          "amplitude_before_v": 0.0751514343904727,
          "amplitude_before_uv": 75151.4343904727,
          "amplitude_after_v": 0.14431380080195522,
          "amplitude_after_uv": 144313.80080195522,
          "relative_error_before": 0.4989904373968487,
          "relative_error_after": 0.03790799465363186,
          "generator_voltage_before_v": 0.0948112104742676,
          "generator_voltage_after_v": 0.18924032104374375
        },
        {
          "frequency_hz": 1000.0,
          "enabled": true,
          "target_amp_v": 0.15,
          "target_amp_uv": 150000.0,
          "tolerance": 0.05,
          "tolerance_percent": 5.0,
          "target_reached": true,
          "steps_count": 2,
          "amplitude_before_v": 0.12808591441888112,
          "amplitude_before_uv": 128085.91441888112,
          "amplitude_after_v": 0.1470671241350588,
          "amplitude_after_uv": 147067.12413505878,
          "relative_error_before": 0.14609390387412585,
          "relative_error_after": 0.01955250576627469,
          "generator_voltage_before_v": 0.18924032104374375,
          "generator_voltage_after_v": 0.22161725030520266
        },
        {
          "frequency_hz": 1050.0,
          "enabled": true,
          "target_amp_v": 0.15,
          "target_amp_uv": 150000.0,
          "tolerance": 0.05,
          "tolerance_percent": 5.0,
          "target_reached": true,
          "steps_count": 2,
          "amplitude_before_v": 0.2039772072440818,
          "amplitude_before_uv": 203977.2072440818,
          "amplitude_after_v": 0.15565533668698658,
          "amplitude_after_uv": 155655.3366869866,
          "relative_error_before": -0.35984804829387873,
          "relative_error_after": -0.0377022445799106,
          "generator_voltage_before_v": 0.22161725030520266,
          "generator_voltage_after_v": 0.16297206925594832
        },
        {
          "frequency_hz": 1100.0,
          "enabled": true,
          "target_amp_v": 0.15,
          "target_amp_uv": 150000.0,
          "tolerance": 0.05,
          "tolerance_percent": 5.0,
          "target_reached": false,
          "steps_count": 1,
          "amplitude_before_v": 0.2278257063400633,
          "amplitude_before_uv": 227825.7063400633,
          "amplitude_after_v": 0.2278257063400633,
          "amplitude_after_uv": 227825.7063400633,
          "relative_error_before": -0.5188380422670887,
          "relative_error_after": -0.5188380422670887,
          "generator_voltage_before_v": 0.05,
          "generator_voltage_after_v": 0.05
        },
        {
          "frequency_hz": 1150.0,
          "enabled": true,
          "target_amp_v": 0.15,
          "target_amp_uv": 150000.0,
          "tolerance": 0.05,
          "tolerance_percent": 5.0,
          "target_reached": true,
          "steps_count": 3,
          "amplitude_before_v": 0.02333892789536001,
          "amplitude_before_uv": 23338.92789536001,
          "amplitude_after_v": 0.14649198808275754,
          "amplitude_after_uv": 146491.98808275754,
          "relative_error_before": 0.8444071473642666,
          "relative_error_after": 0.023386746114949696,
          "generator_voltage_before_v": 0.05,
          "generator_voltage_after_v": 0.369435069307953
        },
        {
          "frequency_hz": 1200.0,
          "enabled": true,
          "target_amp_v": 0.15,
          "target_amp_uv": 150000.0,
          "tolerance": 0.05,
          "tolerance_percent": 5.0,
          "target_reached": false,
          "steps_count": 3,
          "amplitude_before_v": 0.06173732344801377,
          "amplitude_before_uv": 61737.32344801377,
          "amplitude_after_v": 0.10126982791947566,
          "amplitude_after_uv": 101269.82791947566,
          "relative_error_before": 0.5884178436799081,
          "relative_error_after": 0.3248678138701623,
          "generator_voltage_before_v": 0.369435069307953,
          "generator_voltage_after_v": 1.0
        },
        {
          "frequency_hz": 1250.0,
          "enabled": true,
          "target_amp_v": 0.15,
          "target_amp_uv": 150000.0,
          "tolerance": 0.05,
          "tolerance_percent": 5.0,
          "target_reached": false,
          "steps_count": 1,
          "amplitude_before_v": 0.04961803106986578,
          "amplitude_before_uv": 49618.03106986578,
          "amplitude_after_v": 0.04961803106986578,
          "amplitude_after_uv": 49618.03106986578,
          "relative_error_before": 0.6692131262008948,
          "relative_error_after": 0.6692131262008948,
          "generator_voltage_before_v": 1.0,
          "generator_voltage_after_v": 1.0
        },
        {
          "frequency_hz": 1300.0,
          "enabled": true,
          "target_amp_v": 0.15,
          "target_amp_uv": 150000.0,
          "tolerance": 0.05,
          "tolerance_percent": 5.0,
          "target_reached": true,
          "steps_count": 3,
          "amplitude_before_v": 0.16066976745153558,
          "amplitude_before_uv": 160669.7674515356,
          "amplitude_after_v": 0.155387315906151,
          "amplitude_after_uv": 155387.31590615102,
          "relative_error_before": -0.07113178301023723,
          "relative_error_after": -0.03591543937434013,
          "generator_voltage_before_v": 1.0,
          "generator_voltage_after_v": 0.8863629773808405
        },
        {
          "frequency_hz": 1350.0,
          "enabled": true,
          "target_amp_v": 0.15,
          "target_amp_uv": 150000.0,
          "tolerance": 0.05,
          "tolerance_percent": 5.0,
          "target_reached": true,
          "steps_count": 4,
          "amplitude_before_v": 0.20079334614954805,
          "amplitude_before_uv": 200793.34614954804,
          "amplitude_after_v": 0.15346007967775382,
          "amplitude_after_uv": 153460.07967775382,
          "relative_error_before": -0.33862230766365375,
          "relative_error_after": -0.0230671978516922,
          "generator_voltage_before_v": 0.8863629773808405,
          "generator_voltage_after_v": 0.48401654075622175
        },
        {
          "frequency_hz": 1400.0,
          "enabled": true,
          "target_amp_v": 0.15,
          "target_amp_uv": 150000.0,
          "tolerance": 0.05,
          "tolerance_percent": 5.0,
          "target_reached": true,
          "steps_count": 2,
          "amplitude_before_v": 0.13120777490225724,
          "amplitude_before_uv": 131207.77490225725,
          "amplitude_after_v": 0.14612342833432257,
          "amplitude_after_uv": 146123.42833432258,
          "relative_error_before": 0.12528150065161836,
          "relative_error_after": 0.025843811104516168,
          "generator_voltage_before_v": 0.48401654075622175,
          "generator_voltage_after_v": 0.5533397785837377
        },
        {
          "frequency_hz": 1450.0,
          "enabled": true,
          "target_amp_v": 0.15,
          "target_amp_uv": 150000.0,
          "tolerance": 0.05,
          "tolerance_percent": 5.0,
          "target_reached": true,
          "steps_count": 3,
          "amplitude_before_v": 0.19507920168956663,
          "amplitude_before_uv": 195079.20168956663,
          "amplitude_after_v": 0.15158495036913944,
          "amplitude_after_uv": 151584.95036913943,
          "relative_error_before": -0.3005280112637776,
          "relative_error_after": -0.010566335794262954,
          "generator_voltage_before_v": 0.5533397785837377,
          "generator_voltage_after_v": 0.4037542320382947
        },
        {
          "frequency_hz": 1500.0,
          "enabled": true,
          "target_amp_v": 0.15,
          "target_amp_uv": 150000.0,
          "tolerance": 0.05,
          "tolerance_percent": 5.0,
          "target_reached": true,
          "steps_count": 2,
          "amplitude_before_v": 0.31811295143510104,
          "amplitude_before_uv": 318112.95143510104,
          "amplitude_after_v": 0.15087094616057642,
          "amplitude_after_uv": 150870.94616057642,
          "relative_error_before": -1.1207530095673404,
          "relative_error_after": -0.005806307737176164,
          "generator_voltage_before_v": 0.4037542320382947,
          "generator_voltage_after_v": 0.19038248688818146
        },
        {
          "frequency_hz": 1550.0,
          "enabled": true,
          "target_amp_v": 0.15,
          "target_amp_uv": 150000.0,
          "tolerance": 0.05,
          "tolerance_percent": 5.0,
          "target_reached": true,
          "steps_count": 2,
          "amplitude_before_v": 0.3818535231214022,
          "amplitude_before_uv": 381853.5231214022,
          "amplitude_after_v": 0.14745429425841894,
          "amplitude_after_uv": 147454.29425841893,
          "relative_error_before": -1.5456901541426813,
          "relative_error_after": 0.016971371610540374,
          "generator_voltage_before_v": 0.19038248688818146,
          "generator_voltage_after_v": 0.0747861975966979
        },
        {
          "frequency_hz": 1600.0,
          "enabled": true,
          "target_amp_v": 0.15,
          "target_amp_uv": 150000.0,
          "tolerance": 0.05,
          "tolerance_percent": 5.0,
          "target_reached": true,
          "steps_count": 3,
          "amplitude_before_v": 0.03482013051977793,
          "amplitude_before_uv": 34820.13051977793,
          "amplitude_after_v": 0.14931581564220386,
          "amplitude_after_uv": 149315.81564220387,
          "relative_error_before": 0.7678657965348139,
          "relative_error_after": 0.004561229051974203,
          "generator_voltage_before_v": 0.0747861975966979,
          "generator_voltage_after_v": 0.29350300441115856
        },
        {
          "frequency_hz": 1650.0,
          "enabled": true,
          "target_amp_v": 0.15,
          "target_amp_uv": 150000.0,
          "tolerance": 0.05,
          "tolerance_percent": 5.0,
          "target_reached": true,
          "steps_count": 2,
          "amplitude_before_v": 0.11032991570691496,
          "amplitude_before_uv": 110329.91570691495,
          "amplitude_after_v": 0.1505644072379552,
          "amplitude_after_uv": 150564.4072379552,
          "relative_error_before": 0.26446722862056693,
          "relative_error_after": -0.003762714919701334,
          "generator_voltage_before_v": 0.29350300441115856,
          "generator_voltage_after_v": 0.3990345717133131
        },
        {
          "frequency_hz": 1700.0,
          "enabled": true,
          "target_amp_v": 0.15,
          "target_amp_uv": 150000.0,
          "tolerance": 0.05,
          "tolerance_percent": 5.0,
          "target_reached": true,
          "steps_count": 2,
          "amplitude_before_v": 0.19297129269668628,
          "amplitude_before_uv": 192971.2926966863,
          "amplitude_after_v": 0.14971340053298707,
          "amplitude_after_uv": 149713.40053298706,
          "relative_error_before": -0.2864752846445753,
          "relative_error_after": 0.0019106631134195122,
          "generator_voltage_before_v": 0.3990345717133131,
          "generator_voltage_after_v": 0.3101766325977181
        },
        {
          "frequency_hz": 1750.0,
          "enabled": true,
          "target_amp_v": 0.15,
          "target_amp_uv": 150000.0,
          "tolerance": 0.05,
          "tolerance_percent": 5.0,
          "target_reached": true,
          "steps_count": 2,
          "amplitude_before_v": 0.11990042268950565,
          "amplitude_before_uv": 119900.42268950565,
          "amplitude_after_v": 0.15136782255182663,
          "amplitude_after_uv": 151367.82255182663,
          "relative_error_before": 0.20066384873662896,
          "relative_error_after": -0.009118817012177538,
          "generator_voltage_before_v": 0.05,
          "generator_voltage_after_v": 0.06255190625440464
        },
        {
          "frequency_hz": 1800.0,
          "enabled": true,
          "target_amp_v": 0.15,
          "target_amp_uv": 150000.0,
          "tolerance": 0.05,
          "tolerance_percent": 5.0,
          "target_reached": true,
          "steps_count": 3,
          "amplitude_before_v": 0.0428685445880178,
          "amplitude_before_uv": 42868.5445880178,
          "amplitude_after_v": 0.14909247789549307,
          "amplitude_after_uv": 149092.47789549307,
          "relative_error_before": 0.7142097027465479,
          "relative_error_after": 0.006050147363379499,
          "generator_voltage_before_v": 0.06255190625440464,
          "generator_voltage_after_v": 0.2312458291797487
        },
        {
          "frequency_hz": 1850.0,
          "enabled": true,
          "target_amp_v": 0.15,
          "target_amp_uv": 150000.0,
          "tolerance": 0.05,
          "tolerance_percent": 5.0,
          "target_reached": true,
          "steps_count": 2,
          "amplitude_before_v": 0.08944524348148483,
          "amplitude_before_uv": 89445.24348148484,
          "amplitude_after_v": 0.14433698730701858,
          "amplitude_after_uv": 144336.98730701857,
          "relative_error_before": 0.4036983767901011,
          "relative_error_after": 0.03775341795320945,
          "generator_voltage_before_v": 0.2312458291797487,
          "generator_voltage_after_v": 0.3878001001110214
        },
        {
          "frequency_hz": 1900.0,
          "enabled": true,
          "target_amp_v": 0.15,
          "target_amp_uv": 150000.0,
          "tolerance": 0.05,
          "tolerance_percent": 5.0,
          "target_reached": true,
          "steps_count": 2,
          "amplitude_before_v": 0.16161866420790338,
          "amplitude_before_uv": 161618.66420790338,
          "amplitude_after_v": 0.14970853084371186,
          "amplitude_after_uv": 149708.53084371187,
          "relative_error_before": -0.0774577613860226,
          "relative_error_after": 0.001943127708587585,
          "generator_voltage_before_v": 0.3878001001110214,
          "generator_voltage_after_v": 0.35992139460739764
        },
        {
          "frequency_hz": 1950.0,
          "enabled": true,
          "target_amp_v": 0.15,
          "target_amp_uv": 150000.0,
          "tolerance": 0.05,
          "tolerance_percent": 5.0,
          "target_reached": true,
          "steps_count": 2,
          "amplitude_before_v": 0.06014885412200353,
          "amplitude_before_uv": 60148.854122003526,
          "amplitude_after_v": 0.15007772341283826,
          "amplitude_after_uv": 150077.72341283827,
          "relative_error_before": 0.5990076391866432,
          "relative_error_after": -0.0005181560855884356,
          "generator_voltage_before_v": 0.05,
          "generator_voltage_after_v": 0.12469065469913375
        },
        {
          "frequency_hz": 2000.0,
          "enabled": true,
          "target_amp_v": 0.15,
          "target_amp_uv": 150000.0,
          "tolerance": 0.05,
          "tolerance_percent": 5.0,
          "target_reached": true,
          "steps_count": 2,
          "amplitude_before_v": 0.11588901512852164,
          "amplitude_before_uv": 115889.01512852164,
          "amplitude_after_v": 0.14958250379077412,
          "amplitude_after_uv": 149582.50379077412,
          "relative_error_before": 0.22740656580985574,
          "relative_error_after": 0.0027833080615058403,
          "generator_voltage_before_v": 0.12469065469913375,
          "generator_voltage_after_v": 0.1613923302736352
        }
      ]
    },
    {
      "source_file": "konvention_regelung_toleranz_1p0pct_20260625_143912.json",
      "created_at": "2026-06-25T14:39:12",
      "mode": "automatic",
      "purpose": "Referenzdaten für späteren Vergleich",
      "name": "regelung_toleranz",
      "target_amp_v": 0.25,
      "target_amp_uv": 250000.0,
      "tolerance": 0.01,
      "tolerance_percent": 1.0,
      "min_generator_voltage_v": 0.05,
      "max_generator_voltage_v": 1.0,
      "max_auto_steps": 15,
      "sweep_start_freq_hz": 350.0,
      "sweep_stop_freq_hz": 2050.0,
      "sweep_step_freq_hz": 50.0,
      "duration_s": 1.0,
      "frequencies": [
        {
          "frequency_hz": 350.0,
          "enabled": true,
          "target_amp_v": 0.25,
          "target_amp_uv": 250000.0,
          "tolerance": 0.01,
          "tolerance_percent": 1.0,
          "target_reached": true,
          "steps_count": 3,
          "amplitude_before_v": 0.06906858677775278,
          "amplitude_before_uv": 69068.58677775277,
          "amplitude_after_v": 0.2486525895675605,
          "amplitude_after_uv": 248652.5895675605,
          "relative_error_before": 0.7237256528889888,
          "relative_error_after": 0.005389641729757977,
          "generator_voltage_before_v": 0.05,
          "generator_voltage_after_v": 0.19215554885497027
        },
        {
          "frequency_hz": 400.0,
          "enabled": true,
          "target_amp_v": 0.25,
          "target_amp_uv": 250000.0,
          "tolerance": 0.01,
          "tolerance_percent": 1.0,
          "target_reached": true,
          "steps_count": 2,
          "amplitude_before_v": 0.1980989516543587,
          "amplitude_before_uv": 198098.9516543587,
          "amplitude_after_v": 0.2500627217226933,
          "amplitude_after_uv": 250062.72172269327,
          "relative_error_before": 0.2076041933825652,
          "relative_error_after": -0.00025088689077312765,
          "generator_voltage_before_v": 0.05,
          "generator_voltage_after_v": 0.06309977864873707
        },
        {
          "frequency_hz": 450.0,
          "enabled": true,
          "target_amp_v": 0.25,
          "target_amp_uv": 250000.0,
          "tolerance": 0.01,
          "tolerance_percent": 1.0,
          "target_reached": true,
          "steps_count": 2,
          "amplitude_before_v": 0.2154543612951294,
          "amplitude_before_uv": 215454.3612951294,
          "amplitude_after_v": 0.24790722802863552,
          "amplitude_after_uv": 247907.22802863552,
          "relative_error_before": 0.13818255481948238,
          "relative_error_after": 0.008371087885457928,
          "generator_voltage_before_v": 0.06309977864873707,
          "generator_voltage_after_v": 0.07321710531773609
        },
        {
          "frequency_hz": 500.0,
          "enabled": true,
          "target_amp_v": 0.25,
          "target_amp_uv": 250000.0,
          "tolerance": 0.01,
          "tolerance_percent": 1.0,
          "target_reached": true,
          "steps_count": 4,
          "amplitude_before_v": 0.10254037361448881,
          "amplitude_before_uv": 102540.37361448881,
          "amplitude_after_v": 0.24912674216765318,
          "amplitude_after_uv": 249126.7421676532,
          "relative_error_before": 0.5898385055420448,
          "relative_error_after": 0.003493031329387275,
          "generator_voltage_before_v": 0.07321710531773609,
          "generator_voltage_after_v": 0.1949292966757303
        },
        {
          "frequency_hz": 550.0,
          "enabled": true,
          "target_amp_v": 0.25,
          "target_amp_uv": 250000.0,
          "tolerance": 0.01,
          "tolerance_percent": 1.0,
          "target_reached": true,
          "steps_count": 4,
          "amplitude_before_v": 0.1881370354647308,
          "amplitude_before_uv": 188137.03546473078,
          "amplitude_after_v": 0.24872399451038824,
          "amplitude_after_uv": 248723.99451038823,
          "relative_error_before": 0.24745185814107684,
          "relative_error_after": 0.005104021958447058,
          "generator_voltage_before_v": 0.1949292966757303,
          "generator_voltage_after_v": 0.27002367696854496
        },
        {
          "frequency_hz": 600.0,
          "enabled": true,
          "target_amp_v": 0.25,
          "target_amp_uv": 250000.0,
          "tolerance": 0.01,
          "tolerance_percent": 1.0,
          "target_reached": true,
          "steps_count": 3,
          "amplitude_before_v": 0.34465314451815454,
          "amplitude_before_uv": 344653.14451815456,
          "amplitude_after_v": 0.2509288313205952,
          "amplitude_after_uv": 250928.83132059517,
          "relative_error_before": -0.37861257807261817,
          "relative_error_after": -0.0037153252823807215,
          "generator_voltage_before_v": 0.27002367696854496,
          "generator_voltage_after_v": 0.19293109461543903
        },
        {
          "frequency_hz": 650.0,
          "enabled": true,
          "target_amp_v": 0.25,
          "target_amp_uv": 250000.0,
          "tolerance": 0.01,
          "tolerance_percent": 1.0,
          "target_reached": false,
          "steps_count": 1,
          "amplitude_before_v": 0.3141443166910328,
          "amplitude_before_uv": 314144.31669103284,
          "amplitude_after_v": 0.3141443166910328,
          "amplitude_after_uv": 314144.31669103284,
          "relative_error_before": -0.2565772667641313,
          "relative_error_after": -0.2565772667641313,
          "generator_voltage_before_v": 0.05,
          "generator_voltage_after_v": 0.05
        },
        {
          "frequency_hz": 700.0,
          "enabled": true,
          "target_amp_v": 0.25,
          "target_amp_uv": 250000.0,
          "tolerance": 0.01,
          "tolerance_percent": 1.0,
          "target_reached": true,
          "steps_count": 3,
          "amplitude_before_v": 0.05056522976568259,
          "amplitude_before_uv": 50565.22976568259,
          "amplitude_after_v": 0.24764104882281548,
          "amplitude_after_uv": 247641.04882281547,
          "relative_error_before": 0.7977390809372696,
          "relative_error_after": 0.00943580470873806,
          "generator_voltage_before_v": 0.05,
          "generator_voltage_after_v": 0.25686016931691513
        },
        {
          "frequency_hz": 750.0,
          "enabled": true,
          "target_amp_v": 0.25,
          "target_amp_uv": 250000.0,
          "tolerance": 0.01,
          "tolerance_percent": 1.0,
          "target_reached": true,
          "steps_count": 4,
          "amplitude_before_v": 0.1676146628978299,
          "amplitude_before_uv": 167614.6628978299,
          "amplitude_after_v": 0.24803019416575595,
          "amplitude_after_uv": 248030.19416575594,
          "relative_error_before": 0.32954134840868043,
          "relative_error_after": 0.007879223336976215,
          "generator_voltage_before_v": 0.25686016931691513,
          "generator_voltage_after_v": 0.40034850324394006
        },
        {
          "frequency_hz": 800.0,
          "enabled": true,
          "target_amp_v": 0.25,
          "target_amp_uv": 250000.0,
          "tolerance": 0.01,
          "tolerance_percent": 1.0,
          "target_reached": true,
          "steps_count": 3,
          "amplitude_before_v": 0.2982849922956196,
          "amplitude_before_uv": 298284.9922956196,
          "amplitude_after_v": 0.2513190260580939,
          "amplitude_after_uv": 251319.0260580939,
          "relative_error_before": -0.19313996918247844,
          "relative_error_after": -0.005276104232375678,
          "generator_voltage_before_v": 0.40034850324394006,
          "generator_voltage_after_v": 0.32916315652938566
        },
        {
          "frequency_hz": 850.0,
          "enabled": true,
          "target_amp_v": 0.25,
          "target_amp_uv": 250000.0,
          "tolerance": 0.01,
          "tolerance_percent": 1.0,
          "target_reached": true,
          "steps_count": 3,
          "amplitude_before_v": 0.12886241185489963,
          "amplitude_before_uv": 128862.41185489963,
          "amplitude_after_v": 0.2500092439751921,
          "amplitude_after_uv": 250009.24397519208,
          "relative_error_before": 0.48455035258040147,
          "relative_error_after": -3.697590076834345e-05,
          "generator_voltage_before_v": 0.05,
          "generator_voltage_after_v": 0.09804056490854064
        },
        {
          "frequency_hz": 900.0,
          "enabled": true,
          "target_amp_v": 0.25,
          "target_amp_uv": 250000.0,
          "tolerance": 0.01,
          "tolerance_percent": 1.0,
          "target_reached": true,
          "steps_count": 3,
          "amplitude_before_v": 0.15466740705262286,
          "amplitude_before_uv": 154667.40705262285,
          "amplitude_after_v": 0.24976629023002134,
          "amplitude_after_uv": 249766.29023002135,
          "relative_error_before": 0.38133037178950857,
          "relative_error_after": 0.0009348390799146511,
          "generator_voltage_before_v": 0.09804056490854064,
          "generator_voltage_after_v": 0.1604742702174394
        },
        {
          "frequency_hz": 950.0,
          "enabled": true,
          "target_amp_v": 0.25,
          "target_amp_uv": 250000.0,
          "tolerance": 0.01,
          "tolerance_percent": 1.0,
          "target_reached": true,
          "steps_count": 4,
          "amplitude_before_v": 0.12407364176633695,
          "amplitude_before_uv": 124073.64176633695,
          "amplitude_after_v": 0.24969837482604373,
          "amplitude_after_uv": 249698.37482604373,
          "relative_error_before": 0.5037054329346522,
          "relative_error_after": 0.0012065006958250635,
          "generator_voltage_before_v": 0.1604742702174394,
          "generator_voltage_after_v": 0.3496960263544088
        },
        {
          "frequency_hz": 1000.0,
          "enabled": true,
          "target_amp_v": 0.25,
          "target_amp_uv": 250000.0,
          "tolerance": 0.01,
          "tolerance_percent": 1.0,
          "target_reached": true,
          "steps_count": 3,
          "amplitude_before_v": 0.2144834900640995,
          "amplitude_before_uv": 214483.4900640995,
          "amplitude_after_v": 0.2485053578178281,
          "amplitude_after_uv": 248505.3578178281,
          "relative_error_before": 0.142066039743602,
          "relative_error_after": 0.005978568728687628,
          "generator_voltage_before_v": 0.3496960263544088,
          "generator_voltage_after_v": 0.4202321609678595
        },
        {
          "frequency_hz": 1050.0,
          "enabled": true,
          "target_amp_v": 0.25,
          "target_amp_uv": 250000.0,
          "tolerance": 0.01,
          "tolerance_percent": 1.0,
          "target_reached": true,
          "steps_count": 4,
          "amplitude_before_v": 0.3397708976934821,
          "amplitude_before_uv": 339770.8976934821,
          "amplitude_after_v": 0.2508416630613751,
          "amplitude_after_uv": 250841.66306137512,
          "relative_error_before": -0.3590835907739285,
          "relative_error_after": -0.003366652245500479,
          "generator_voltage_before_v": 0.4202321609678595,
          "generator_voltage_after_v": 0.2875987939432141
        },
        {
          "frequency_hz": 1100.0,
          "enabled": true,
          "target_amp_v": 0.25,
          "target_amp_uv": 250000.0,
          "tolerance": 0.01,
          "tolerance_percent": 1.0,
          "target_reached": true,
          "steps_count": 3,
          "amplitude_before_v": 0.23888174407840326,
          "amplitude_before_uv": 238881.74407840325,
          "amplitude_after_v": 0.25122033953168765,
          "amplitude_after_uv": 251220.33953168764,
          "relative_error_before": 0.04447302368638695,
          "relative_error_after": -0.004881358126750612,
          "generator_voltage_before_v": 0.05,
          "generator_voltage_after_v": 0.05
        },
        {
          "frequency_hz": 1150.0,
          "enabled": true,
          "target_amp_v": 0.25,
          "target_amp_uv": 250000.0,
          "tolerance": 0.01,
          "tolerance_percent": 1.0,
          "target_reached": false,
          "steps_count": 4,
          "amplitude_before_v": 0.023595808632301048,
          "amplitude_before_uv": 23595.808632301047,
          "amplitude_after_v": 0.24632855593762262,
          "amplitude_after_uv": 246328.55593762262,
          "relative_error_before": 0.9056167654707958,
          "relative_error_after": 0.014685776249509508,
          "generator_voltage_before_v": 0.05,
          "generator_voltage_after_v": 1.0
        },
        {
          "frequency_hz": 1200.0,
          "enabled": true,
          "target_amp_v": 0.25,
          "target_amp_uv": 250000.0,
          "tolerance": 0.01,
          "tolerance_percent": 1.0,
          "target_reached": false,
          "steps_count": 1,
          "amplitude_before_v": 0.10283982782384059,
          "amplitude_before_uv": 102839.82782384059,
          "amplitude_after_v": 0.10283982782384059,
          "amplitude_after_uv": 102839.82782384059,
          "relative_error_before": 0.5886406887046376,
          "relative_error_after": 0.5886406887046376,
          "generator_voltage_before_v": 1.0,
          "generator_voltage_after_v": 1.0
        },
        {
          "frequency_hz": 1250.0,
          "enabled": true,
          "target_amp_v": 0.25,
          "target_amp_uv": 250000.0,
          "tolerance": 0.01,
          "tolerance_percent": 1.0,
          "target_reached": false,
          "steps_count": 1,
          "amplitude_before_v": 0.050573416907435234,
          "amplitude_before_uv": 50573.41690743523,
          "amplitude_after_v": 0.050573416907435234,
          "amplitude_after_uv": 50573.41690743523,
          "relative_error_before": 0.7977063323702591,
          "relative_error_after": 0.7977063323702591,
          "generator_voltage_before_v": 1.0,
          "generator_voltage_after_v": 1.0
        },
        {
          "frequency_hz": 1300.0,
          "enabled": true,
          "target_amp_v": 0.25,
          "target_amp_uv": 250000.0,
          "tolerance": 0.01,
          "tolerance_percent": 1.0,
          "target_reached": false,
          "steps_count": 1,
          "amplitude_before_v": 0.14825197221450295,
          "amplitude_before_uv": 148251.97221450295,
          "amplitude_after_v": 0.14825197221450295,
          "amplitude_after_uv": 148251.97221450295,
          "relative_error_before": 0.4069921111419882,
          "relative_error_after": 0.4069921111419882,
          "generator_voltage_before_v": 1.0,
          "generator_voltage_after_v": 1.0
        },
        {
          "frequency_hz": 1350.0,
          "enabled": true,
          "target_amp_v": 0.25,
          "target_amp_uv": 250000.0,
          "tolerance": 0.01,
          "tolerance_percent": 1.0,
          "target_reached": false,
          "steps_count": 1,
          "amplitude_before_v": 0.20582259745284612,
          "amplitude_before_uv": 205822.59745284612,
          "amplitude_after_v": 0.20582259745284612,
          "amplitude_after_uv": 205822.59745284612,
          "relative_error_before": 0.17670961018861553,
          "relative_error_after": 0.17670961018861553,
          "generator_voltage_before_v": 1.0,
          "generator_voltage_after_v": 1.0
        },
        {
          "frequency_hz": 1400.0,
          "enabled": true,
          "target_amp_v": 0.25,
          "target_amp_uv": 250000.0,
          "tolerance": 0.01,
          "tolerance_percent": 1.0,
          "target_reached": false,
          "steps_count": 1,
          "amplitude_before_v": 0.17235371487404633,
          "amplitude_before_uv": 172353.71487404633,
          "amplitude_after_v": 0.17235371487404633,
          "amplitude_after_uv": 172353.71487404633,
          "relative_error_before": 0.3105851405038147,
          "relative_error_after": 0.3105851405038147,
          "generator_voltage_before_v": 1.0,
          "generator_voltage_after_v": 1.0
        },
        {
          "frequency_hz": 1450.0,
          "enabled": true,
          "target_amp_v": 0.25,
          "target_amp_uv": 250000.0,
          "tolerance": 0.01,
          "tolerance_percent": 1.0,
          "target_reached": false,
          "steps_count": 1,
          "amplitude_before_v": 0.231401557474736,
          "amplitude_before_uv": 231401.557474736,
          "amplitude_after_v": 0.231401557474736,
          "amplitude_after_uv": 231401.557474736,
          "relative_error_before": 0.07439377010105597,
          "relative_error_after": 0.07439377010105597,
          "generator_voltage_before_v": 1.0,
          "generator_voltage_after_v": 1.0
        },
        {
          "frequency_hz": 1500.0,
          "enabled": true,
          "target_amp_v": 0.25,
          "target_amp_uv": 250000.0,
          "tolerance": 0.01,
          "tolerance_percent": 1.0,
          "target_reached": true,
          "steps_count": 3,
          "amplitude_before_v": 0.036696579547233085,
          "amplitude_before_uv": 36696.57954723309,
          "amplitude_after_v": 0.25092771669521585,
          "amplitude_after_uv": 250927.71669521584,
          "relative_error_before": 0.8532136818110676,
          "relative_error_after": -0.003710866780863409,
          "generator_voltage_before_v": 0.05,
          "generator_voltage_after_v": 0.3231834260092192
        },
        {
          "frequency_hz": 1550.0,
          "enabled": true,
          "target_amp_v": 0.25,
          "target_amp_uv": 250000.0,
          "tolerance": 0.01,
          "tolerance_percent": 1.0,
          "target_reached": true,
          "steps_count": 3,
          "amplitude_before_v": 0.10236995701943731,
          "amplitude_before_uv": 102369.95701943731,
          "amplitude_after_v": 0.2497703562360461,
          "amplitude_after_uv": 249770.3562360461,
          "relative_error_before": 0.5905201719222508,
          "relative_error_after": 0.0009185750558156069,
          "generator_voltage_before_v": 0.05,
          "generator_voltage_after_v": 0.11894062813027499
        },
        {
          "frequency_hz": 1600.0,
          "enabled": true,
          "target_amp_v": 0.25,
          "target_amp_uv": 250000.0,
          "tolerance": 0.01,
          "tolerance_percent": 1.0,
          "target_reached": true,
          "steps_count": 3,
          "amplitude_before_v": 0.05746483504033007,
          "amplitude_before_uv": 57464.83504033007,
          "amplitude_after_v": 0.24804712571933055,
          "amplitude_after_uv": 248047.12571933054,
          "relative_error_before": 0.7701406598386797,
          "relative_error_after": 0.007811497122677813,
          "generator_voltage_before_v": 0.11894062813027499,
          "generator_voltage_after_v": 0.4883570360896049
        },
        {
          "frequency_hz": 1650.0,
          "enabled": true,
          "target_amp_v": 0.25,
          "target_amp_uv": 250000.0,
          "tolerance": 0.01,
          "tolerance_percent": 1.0,
          "target_reached": true,
          "steps_count": 14,
          "amplitude_before_v": 0.18095756608406566,
          "amplitude_before_uv": 180957.56608406565,
          "amplitude_after_v": 0.2475566185616748,
          "amplitude_after_uv": 247556.61856167478,
          "relative_error_before": 0.27616973566373737,
          "relative_error_after": 0.009773525753300816,
          "generator_voltage_before_v": 0.4883570360896049,
          "generator_voltage_after_v": 0.9158150011903253
        },
        {
          "frequency_hz": 1700.0,
          "enabled": true,
          "target_amp_v": 0.25,
          "target_amp_uv": 250000.0,
          "tolerance": 0.01,
          "tolerance_percent": 1.0,
          "target_reached": true,
          "steps_count": 5,
          "amplitude_before_v": 0.3104890665169316,
          "amplitude_before_uv": 310489.0665169316,
          "amplitude_after_v": 0.2509007584402281,
          "amplitude_after_uv": 250900.7584402281,
          "relative_error_before": -0.24195626606772636,
          "relative_error_after": -0.003603033760912311,
          "generator_voltage_before_v": 0.9158150011903253,
          "generator_voltage_after_v": 0.5591631030116342
        },
        {
          "frequency_hz": 1750.0,
          "enabled": true,
          "target_amp_v": 0.25,
          "target_amp_uv": 250000.0,
          "tolerance": 0.01,
          "tolerance_percent": 1.0,
          "target_reached": true,
          "steps_count": 5,
          "amplitude_before_v": 0.0991261677360734,
          "amplitude_before_uv": 99126.1677360734,
          "amplitude_after_v": 0.2523957177804838,
          "amplitude_after_uv": 252395.7177804838,
          "relative_error_before": 0.6034953290557064,
          "relative_error_after": -0.009582871121935232,
          "generator_voltage_before_v": 0.05,
          "generator_voltage_after_v": 0.11703510948139663
        },
        {
          "frequency_hz": 1800.0,
          "enabled": true,
          "target_amp_v": 0.25,
          "target_amp_uv": 250000.0,
          "tolerance": 0.01,
          "tolerance_percent": 1.0,
          "target_reached": true,
          "steps_count": 4,
          "amplitude_before_v": 0.07748585731609749,
          "amplitude_before_uv": 77485.85731609749,
          "amplitude_after_v": 0.24862844261598124,
          "amplitude_after_uv": 248628.44261598124,
          "relative_error_before": 0.6900565707356101,
          "relative_error_after": 0.005486229536075027,
          "generator_voltage_before_v": 0.11703510948139663,
          "generator_voltage_after_v": 0.40782717107719973
        },
        {
          "frequency_hz": 1850.0,
          "enabled": true,
          "target_amp_v": 0.25,
          "target_amp_uv": 250000.0,
          "tolerance": 0.01,
          "tolerance_percent": 1.0,
          "target_reached": false,
          "steps_count": 3,
          "amplitude_before_v": 0.14618585803745682,
          "amplitude_before_uv": 146185.8580374568,
          "amplitude_after_v": 0.24002398921759904,
          "amplitude_after_uv": 240023.98921759904,
          "relative_error_before": 0.41525656785017273,
          "relative_error_after": 0.03990404312960383,
          "generator_voltage_before_v": 0.40782717107719973,
          "generator_voltage_after_v": 1.0
        },
        {
          "frequency_hz": 1900.0,
          "enabled": true,
          "target_amp_v": 0.25,
          "target_amp_uv": 250000.0,
          "tolerance": 0.01,
          "tolerance_percent": 1.0,
          "target_reached": true,
          "steps_count": 3,
          "amplitude_before_v": 0.2593363606039115,
          "amplitude_before_uv": 259336.3606039115,
          "amplitude_after_v": 0.25225743064884876,
          "amplitude_after_uv": 252257.43064884876,
          "relative_error_before": -0.03734544241564608,
          "relative_error_after": -0.009029722595395029,
          "generator_voltage_before_v": 1.0,
          "generator_voltage_after_v": 0.9473950658707893
        },
        {
          "frequency_hz": 1950.0,
          "enabled": true,
          "target_amp_v": 0.25,
          "target_amp_uv": 250000.0,
          "tolerance": 0.01,
          "tolerance_percent": 1.0,
          "target_reached": true,
          "steps_count": 2,
          "amplitude_before_v": 0.05209232910012735,
          "amplitude_before_uv": 52092.329100127354,
          "amplitude_after_v": 0.2524429511898855,
          "amplitude_after_uv": 252442.95118988553,
          "relative_error_before": 0.7916306835994906,
          "relative_error_after": -0.009771804759542091,
          "generator_voltage_before_v": 0.05,
          "generator_voltage_after_v": 0.2399585546603921
        },
        {
          "frequency_hz": 2000.0,
          "enabled": true,
          "target_amp_v": 0.25,
          "target_amp_uv": 250000.0,
          "tolerance": 0.01,
          "tolerance_percent": 1.0,
          "target_reached": true,
          "steps_count": 2,
          "amplitude_before_v": 0.21329575450310212,
          "amplitude_before_uv": 213295.75450310213,
          "amplitude_after_v": 0.2503670247464368,
          "amplitude_after_uv": 250367.0247464368,
          "relative_error_before": 0.14681698198759152,
          "relative_error_after": -0.0014680989857471793,
          "generator_voltage_before_v": 0.2399585546603921,
          "generator_voltage_after_v": 0.2812509738160039
        }
      ]
    },
    {
      "source_file": "konvention_regelung_toleranz_0p0pct_20260625_145711.json",
      "created_at": "2026-06-25T14:57:11",
      "mode": "automatic",
      "purpose": "Referenzdaten für späteren Vergleich",
      "name": "regelung_toleranz",
      "target_amp_v": 0.25,
      "target_amp_uv": 250000.0,
      "tolerance": 0.0,
      "tolerance_percent": 0.0,
      "min_generator_voltage_v": 0.05,
      "max_generator_voltage_v": 1.0,
      "max_auto_steps": 15,
      "sweep_start_freq_hz": 350.0,
      "sweep_stop_freq_hz": 2050.0,
      "sweep_step_freq_hz": 50.0,
      "duration_s": 1.0,
      "frequencies": [
        {
          "frequency_hz": 350.0,
          "enabled": true,
          "target_amp_v": 0.25,
          "target_amp_uv": 250000.0,
          "tolerance": 0.0,
          "tolerance_percent": 0.0,
          "target_reached": false,
          "steps_count": 15,
          "amplitude_before_v": 0.06897823522696733,
          "amplitude_before_uv": 68978.23522696733,
          "amplitude_after_v": 0.25014311452044624,
          "amplitude_after_uv": 250143.11452044625,
          "relative_error_before": 0.7240870590921307,
          "relative_error_after": -0.0005724580817849656,
          "generator_voltage_before_v": 0.05,
          "generator_voltage_after_v": 0.1921093993434536
        },
        {
          "frequency_hz": 400.0,
          "enabled": true,
          "target_amp_v": 0.25,
          "target_amp_uv": 250000.0,
          "tolerance": 0.0,
          "tolerance_percent": 0.0,
          "target_reached": false,
          "steps_count": 14,
          "amplitude_before_v": 0.19603287539636838,
          "amplitude_before_uv": 196032.87539636838,
          "amplitude_after_v": 0.25041289825974183,
          "amplitude_after_uv": 250412.89825974184,
          "relative_error_before": 0.2158684984145265,
          "relative_error_after": -0.0016515930389673361,
          "generator_voltage_before_v": 0.05,
          "generator_voltage_after_v": 0.06370302062362215
        },
        {
          "frequency_hz": 450.0,
          "enabled": true,
          "target_amp_v": 0.25,
          "target_amp_uv": 250000.0,
          "tolerance": 0.0,
          "tolerance_percent": 0.0,
          "target_reached": false,
          "steps_count": 15,
          "amplitude_before_v": 0.21806159699712505,
          "amplitude_before_uv": 218061.59699712505,
          "amplitude_after_v": 0.25014083463300596,
          "amplitude_after_uv": 250140.83463300596,
          "relative_error_before": 0.12775361201149982,
          "relative_error_after": -0.0005633385320238382,
          "generator_voltage_before_v": 0.06370302062362215,
          "generator_voltage_after_v": 0.07362870729582668
        },
        {
          "frequency_hz": 500.0,
          "enabled": true,
          "target_amp_v": 0.25,
          "target_amp_uv": 250000.0,
          "tolerance": 0.0,
          "tolerance_percent": 0.0,
          "target_reached": false,
          "steps_count": 15,
          "amplitude_before_v": 0.10307958697121933,
          "amplitude_before_uv": 103079.58697121932,
          "amplitude_after_v": 0.24954825112331053,
          "amplitude_after_uv": 249548.25112331053,
          "relative_error_before": 0.5876816521151227,
          "relative_error_after": 0.0018069955067578913,
          "generator_voltage_before_v": 0.07362870729582668,
          "generator_voltage_after_v": 0.19774893863256401
        },
        {
          "frequency_hz": 550.0,
          "enabled": true,
          "target_amp_v": 0.25,
          "target_amp_uv": 250000.0,
          "tolerance": 0.0,
          "tolerance_percent": 0.0,
          "target_reached": false,
          "steps_count": 15,
          "amplitude_before_v": 0.18850011641968462,
          "amplitude_before_uv": 188500.1164196846,
          "amplitude_after_v": 0.24984693834486799,
          "amplitude_after_uv": 249846.938344868,
          "relative_error_before": 0.24599953432126154,
          "relative_error_after": 0.0006122466205280563,
          "generator_voltage_before_v": 0.19774893863256401,
          "generator_voltage_after_v": 0.2778134512412446
        },
        {
          "frequency_hz": 600.0,
          "enabled": true,
          "target_amp_v": 0.25,
          "target_amp_uv": 250000.0,
          "tolerance": 0.0,
          "tolerance_percent": 0.0,
          "target_reached": false,
          "steps_count": 15,
          "amplitude_before_v": 0.34777405104539,
          "amplitude_before_uv": 347774.05104539,
          "amplitude_after_v": 0.24998644773129344,
          "amplitude_after_uv": 249986.44773129345,
          "relative_error_before": -0.39109620418156,
          "relative_error_after": 5.4209074826228054e-05,
          "generator_voltage_before_v": 0.2778134512412446,
          "generator_voltage_after_v": 0.19356142993964945
        },
        {
          "frequency_hz": 650.0,
          "enabled": true,
          "target_amp_v": 0.25,
          "target_amp_uv": 250000.0,
          "tolerance": 0.0,
          "tolerance_percent": 0.0,
          "target_reached": false,
          "steps_count": 1,
          "amplitude_before_v": 0.31643173915814826,
          "amplitude_before_uv": 316431.73915814824,
          "amplitude_after_v": 0.31643173915814826,
          "amplitude_after_uv": 316431.73915814824,
          "relative_error_before": -0.26572695663259305,
          "relative_error_after": -0.26572695663259305,
          "generator_voltage_before_v": 0.05,
          "generator_voltage_after_v": 0.05
        },
        {
          "frequency_hz": 700.0,
          "enabled": true,
          "target_amp_v": 0.25,
          "target_amp_uv": 250000.0,
          "tolerance": 0.0,
          "tolerance_percent": 0.0,
          "target_reached": false,
          "steps_count": 15,
          "amplitude_before_v": 0.05049007980792391,
          "amplitude_before_uv": 50490.07980792391,
          "amplitude_after_v": 0.2497247485447511,
          "amplitude_after_uv": 249724.7485447511,
          "relative_error_before": 0.7980396807683043,
          "relative_error_after": 0.001101005820995593,
          "generator_voltage_before_v": 0.05,
          "generator_voltage_after_v": 0.26531854196438653
        },
        {
          "frequency_hz": 750.0,
          "enabled": true,
          "target_amp_v": 0.25,
          "target_amp_uv": 250000.0,
          "tolerance": 0.0,
          "tolerance_percent": 0.0,
          "target_reached": false,
          "steps_count": 15,
          "amplitude_before_v": 0.17019311104084442,
          "amplitude_before_uv": 170193.1110408444,
          "amplitude_after_v": 0.2500621305187975,
          "amplitude_after_uv": 250062.1305187975,
          "relative_error_before": 0.3192275558366223,
          "relative_error_after": -0.00024852207518999414,
          "generator_voltage_before_v": 0.26531854196438653,
          "generator_voltage_after_v": 0.4168436295870449
        },
        {
          "frequency_hz": 800.0,
          "enabled": true,
          "target_amp_v": 0.25,
          "target_amp_uv": 250000.0,
          "tolerance": 0.0,
          "tolerance_percent": 0.0,
          "target_reached": false,
          "steps_count": 5,
          "amplitude_before_v": 0.30344083430417385,
          "amplitude_before_uv": 303440.8343041738,
          "amplitude_after_v": 0.2504163608882699,
          "amplitude_after_uv": 250416.3608882699,
          "relative_error_before": -0.21376333721669538,
          "relative_error_after": -0.0016654435530796263,
          "generator_voltage_before_v": 0.4168436295870449,
          "generator_voltage_after_v": 0.3310173263120115
        },
        {
          "frequency_hz": 850.0,
          "enabled": true,
          "target_amp_v": 0.25,
          "target_amp_uv": 250000.0,
          "tolerance": 0.0,
          "tolerance_percent": 0.0,
          "target_reached": false,
          "steps_count": 14,
          "amplitude_before_v": 0.12671431593529614,
          "amplitude_before_uv": 126714.31593529614,
          "amplitude_after_v": 0.25012835266517724,
          "amplitude_after_uv": 250128.35266517726,
          "relative_error_before": 0.49314273625881544,
          "relative_error_after": -0.0005134106607089794,
          "generator_voltage_before_v": 0.05,
          "generator_voltage_after_v": 0.09983654543113638
        },
        {
          "frequency_hz": 900.0,
          "enabled": true,
          "target_amp_v": 0.25,
          "target_amp_uv": 250000.0,
          "tolerance": 0.0,
          "tolerance_percent": 0.0,
          "target_reached": false,
          "steps_count": 15,
          "amplitude_before_v": 0.15840926955432327,
          "amplitude_before_uv": 158409.26955432328,
          "amplitude_after_v": 0.25007856290001695,
          "amplitude_after_uv": 250078.56290001696,
          "relative_error_before": 0.3663629217827069,
          "relative_error_after": -0.0003142516000678164,
          "generator_voltage_before_v": 0.09983654543113638,
          "generator_voltage_after_v": 0.15967325760530604
        },
        {
          "frequency_hz": 950.0,
          "enabled": true,
          "target_amp_v": 0.25,
          "target_amp_uv": 250000.0,
          "tolerance": 0.0,
          "tolerance_percent": 0.0,
          "target_reached": false,
          "steps_count": 15,
          "amplitude_before_v": 0.1230896128765173,
          "amplitude_before_uv": 123089.6128765173,
          "amplitude_after_v": 0.25012047624004513,
          "amplitude_after_uv": 250120.47624004513,
          "relative_error_before": 0.5076415484939307,
          "relative_error_after": -0.00048190496018052364,
          "generator_voltage_before_v": 0.15967325760530604,
          "generator_voltage_after_v": 0.35029641618814344
        },
        {
          "frequency_hz": 1000.0,
          "enabled": true,
          "target_amp_v": 0.25,
          "target_amp_uv": 250000.0,
          "tolerance": 0.0,
          "tolerance_percent": 0.0,
          "target_reached": false,
          "steps_count": 15,
          "amplitude_before_v": 0.21423128267237568,
          "amplitude_before_uv": 214231.28267237567,
          "amplitude_after_v": 0.24999710500605316,
          "amplitude_after_uv": 249997.10500605314,
          "relative_error_before": 0.1430748693104973,
          "relative_error_after": 1.1579975787379126e-05,
          "generator_voltage_before_v": 0.35029641618814344,
          "generator_voltage_after_v": 0.4244315039569517
        },
        {
          "frequency_hz": 1050.0,
          "enabled": true,
          "target_amp_v": 0.25,
          "target_amp_uv": 250000.0,
          "tolerance": 0.0,
          "tolerance_percent": 0.0,
          "target_reached": false,
          "steps_count": 15,
          "amplitude_before_v": 0.33950623647363104,
          "amplitude_before_uv": 339506.23647363106,
          "amplitude_after_v": 0.2500367590617677,
          "amplitude_after_uv": 250036.7590617677,
          "relative_error_before": -0.35802494589452416,
          "relative_error_after": -0.00014703624707079754,
          "generator_voltage_before_v": 0.4244315039569517,
          "generator_voltage_after_v": 0.2887127417855162
        },
        {
          "frequency_hz": 1100.0,
          "enabled": true,
          "target_amp_v": 0.25,
          "target_amp_uv": 250000.0,
          "tolerance": 0.0,
          "tolerance_percent": 0.0,
          "target_reached": false,
          "steps_count": 3,
          "amplitude_before_v": 0.24649408399162465,
          "amplitude_before_uv": 246494.08399162465,
          "amplitude_after_v": 0.2599501915621759,
          "amplitude_after_uv": 259950.19156217593,
          "relative_error_before": 0.014023664033501415,
          "relative_error_after": -0.039800766248703656,
          "generator_voltage_before_v": 0.05,
          "generator_voltage_after_v": 0.05
        },
        {
          "frequency_hz": 1150.0,
          "enabled": true,
          "target_amp_v": 0.25,
          "target_amp_uv": 250000.0,
          "tolerance": 0.0,
          "tolerance_percent": 0.0,
          "target_reached": false,
          "steps_count": 15,
          "amplitude_before_v": 0.023797225243277997,
          "amplitude_before_uv": 23797.225243277997,
          "amplitude_after_v": 0.24802695631295588,
          "amplitude_after_uv": 248026.95631295588,
          "relative_error_before": 0.904811099026888,
          "relative_error_after": 0.007892174748176495,
          "generator_voltage_before_v": 0.05,
          "generator_voltage_after_v": 0.9609908635033021
        },
        {
          "frequency_hz": 1200.0,
          "enabled": true,
          "target_amp_v": 0.25,
          "target_amp_uv": 250000.0,
          "tolerance": 0.0,
          "tolerance_percent": 0.0,
          "target_reached": false,
          "steps_count": 2,
          "amplitude_before_v": 0.10344100850667454,
          "amplitude_before_uv": 103441.00850667454,
          "amplitude_after_v": 0.10352246136733272,
          "amplitude_after_uv": 103522.46136733271,
          "relative_error_before": 0.5862359659733019,
          "relative_error_after": 0.5859101545306691,
          "generator_voltage_before_v": 0.9609908635033021,
          "generator_voltage_after_v": 1.0
        },
        {
          "frequency_hz": 1250.0,
          "enabled": true,
          "target_amp_v": 0.25,
          "target_amp_uv": 250000.0,
          "tolerance": 0.0,
          "tolerance_percent": 0.0,
          "target_reached": false,
          "steps_count": 1,
          "amplitude_before_v": 0.051605710050625045,
          "amplitude_before_uv": 51605.71005062504,
          "amplitude_after_v": 0.051605710050625045,
          "amplitude_after_uv": 51605.71005062504,
          "relative_error_before": 0.7935771597974999,
          "relative_error_after": 0.7935771597974999,
          "generator_voltage_before_v": 1.0,
          "generator_voltage_after_v": 1.0
        },
        {
          "frequency_hz": 1300.0,
          "enabled": true,
          "target_amp_v": 0.25,
          "target_amp_uv": 250000.0,
          "tolerance": 0.0,
          "tolerance_percent": 0.0,
          "target_reached": false,
          "steps_count": 1,
          "amplitude_before_v": 0.13558122044115367,
          "amplitude_before_uv": 135581.22044115368,
          "amplitude_after_v": 0.13558122044115367,
          "amplitude_after_uv": 135581.22044115368,
          "relative_error_before": 0.4576751182353853,
          "relative_error_after": 0.4576751182353853,
          "generator_voltage_before_v": 1.0,
          "generator_voltage_after_v": 1.0
        },
        {
          "frequency_hz": 1350.0,
          "enabled": true,
          "target_amp_v": 0.25,
          "target_amp_uv": 250000.0,
          "tolerance": 0.0,
          "tolerance_percent": 0.0,
          "target_reached": false,
          "steps_count": 1,
          "amplitude_before_v": 0.20486571252432498,
          "amplitude_before_uv": 204865.71252432498,
          "amplitude_after_v": 0.20486571252432498,
          "amplitude_after_uv": 204865.71252432498,
          "relative_error_before": 0.1805371499027001,
          "relative_error_after": 0.1805371499027001,
          "generator_voltage_before_v": 1.0,
          "generator_voltage_after_v": 1.0
        },
        {
          "frequency_hz": 1400.0,
          "enabled": true,
          "target_amp_v": 0.25,
          "target_amp_uv": 250000.0,
          "tolerance": 0.0,
          "tolerance_percent": 0.0,
          "target_reached": false,
          "steps_count": 1,
          "amplitude_before_v": 0.1713358083725438,
          "amplitude_before_uv": 171335.8083725438,
          "amplitude_after_v": 0.1713358083725438,
          "amplitude_after_uv": 171335.8083725438,
          "relative_error_before": 0.31465676650982477,
          "relative_error_after": 0.31465676650982477,
          "generator_voltage_before_v": 1.0,
          "generator_voltage_after_v": 1.0
        },
        {
          "frequency_hz": 1450.0,
          "enabled": true,
          "target_amp_v": 0.25,
          "target_amp_uv": 250000.0,
          "tolerance": 0.0,
          "tolerance_percent": 0.0,
          "target_reached": false,
          "steps_count": 1,
          "amplitude_before_v": 0.22935067150738137,
          "amplitude_before_uv": 229350.67150738137,
          "amplitude_after_v": 0.22935067150738137,
          "amplitude_after_uv": 229350.67150738137,
          "relative_error_before": 0.08259731397047454,
          "relative_error_after": 0.08259731397047454,
          "generator_voltage_before_v": 1.0,
          "generator_voltage_after_v": 1.0
        },
        {
          "frequency_hz": 1500.0,
          "enabled": true,
          "target_amp_v": 0.25,
          "target_amp_uv": 250000.0,
          "tolerance": 0.0,
          "tolerance_percent": 0.0,
          "target_reached": false,
          "steps_count": 14,
          "amplitude_before_v": 0.03605324790357875,
          "amplitude_before_uv": 36053.24790357875,
          "amplitude_after_v": 0.2503686045127691,
          "amplitude_after_uv": 250368.6045127691,
          "relative_error_before": 0.855787008385685,
          "relative_error_after": -0.0014744180510763982,
          "generator_voltage_before_v": 0.05,
          "generator_voltage_after_v": 0.3275288393121413
        },
        {
          "frequency_hz": 1550.0,
          "enabled": true,
          "target_amp_v": 0.25,
          "target_amp_uv": 250000.0,
          "tolerance": 0.0,
          "tolerance_percent": 0.0,
          "target_reached": false,
          "steps_count": 14,
          "amplitude_before_v": 0.10502132252353268,
          "amplitude_before_uv": 105021.32252353268,
          "amplitude_after_v": 0.2501387282140318,
          "amplitude_after_uv": 250138.7282140318,
          "relative_error_before": 0.5799147099058692,
          "relative_error_after": -0.0005549128561272987,
          "generator_voltage_before_v": 0.05,
          "generator_voltage_after_v": 0.11581245269315908
        },
        {
          "frequency_hz": 1600.0,
          "enabled": true,
          "target_amp_v": 0.25,
          "target_amp_uv": 250000.0,
          "tolerance": 0.0,
          "tolerance_percent": 0.0,
          "target_reached": false,
          "steps_count": 15,
          "amplitude_before_v": 0.05616198883232548,
          "amplitude_before_uv": 56161.988832325485,
          "amplitude_after_v": 0.24970358201654405,
          "amplitude_after_uv": 249703.58201654404,
          "relative_error_before": 0.7753520446706981,
          "relative_error_after": 0.0011856719338237953,
          "generator_voltage_before_v": 0.11581245269315908,
          "generator_voltage_after_v": 0.49643111174888815
        },
        {
          "frequency_hz": 1650.0,
          "enabled": true,
          "target_amp_v": 0.25,
          "target_amp_uv": 250000.0,
          "tolerance": 0.0,
          "tolerance_percent": 0.0,
          "target_reached": false,
          "steps_count": 15,
          "amplitude_before_v": 0.18122149553222236,
          "amplitude_before_uv": 181221.49553222235,
          "amplitude_after_v": 0.24850979485219113,
          "amplitude_after_uv": 248509.79485219112,
          "relative_error_before": 0.27511401787111056,
          "relative_error_after": 0.005960820591235483,
          "generator_voltage_before_v": 0.49643111174888815,
          "generator_voltage_after_v": 1.0
        },
        {
          "frequency_hz": 1700.0,
          "enabled": true,
          "target_amp_v": 0.25,
          "target_amp_uv": 250000.0,
          "tolerance": 0.0,
          "tolerance_percent": 0.0,
          "target_reached": false,
          "steps_count": 15,
          "amplitude_before_v": 0.3093283991799228,
          "amplitude_before_uv": 309328.39917992277,
          "amplitude_after_v": 0.25002705241419587,
          "amplitude_after_uv": 250027.05241419587,
          "relative_error_before": -0.2373135967196911,
          "relative_error_after": -0.00010820965678348671,
          "generator_voltage_before_v": 1.0,
          "generator_voltage_after_v": 0.5644084272056983
        },
        {
          "frequency_hz": 1750.0,
          "enabled": true,
          "target_amp_v": 0.25,
          "target_amp_uv": 250000.0,
          "tolerance": 0.0,
          "tolerance_percent": 0.0,
          "target_reached": false,
          "steps_count": 14,
          "amplitude_before_v": 0.09461409932849514,
          "amplitude_before_uv": 94614.09932849514,
          "amplitude_after_v": 0.2504145235502144,
          "amplitude_after_uv": 250414.52355021436,
          "relative_error_before": 0.6215436026860195,
          "relative_error_after": -0.0016580942008574961,
          "generator_voltage_before_v": 0.05,
          "generator_voltage_after_v": 0.11885058438398934
        },
        {
          "frequency_hz": 1800.0,
          "enabled": true,
          "target_amp_v": 0.25,
          "target_amp_uv": 250000.0,
          "tolerance": 0.0,
          "tolerance_percent": 0.0,
          "target_reached": false,
          "steps_count": 15,
          "amplitude_before_v": 0.08035349377773335,
          "amplitude_before_uv": 80353.49377773335,
          "amplitude_after_v": 0.2500888161082169,
          "amplitude_after_uv": 250088.81610821694,
          "relative_error_before": 0.6785860248890666,
          "relative_error_after": -0.0003552644328677079,
          "generator_voltage_before_v": 0.11885058438398934,
          "generator_voltage_after_v": 0.411229952071758
        },
        {
          "frequency_hz": 1850.0,
          "enabled": true,
          "target_amp_v": 0.25,
          "target_amp_uv": 250000.0,
          "tolerance": 0.0,
          "tolerance_percent": 0.0,
          "target_reached": false,
          "steps_count": 3,
          "amplitude_before_v": 0.14573454589684567,
          "amplitude_before_uv": 145734.54589684567,
          "amplitude_after_v": 0.23879335554157965,
          "amplitude_after_uv": 238793.35554157966,
          "relative_error_before": 0.4170618164126173,
          "relative_error_after": 0.04482657783368138,
          "generator_voltage_before_v": 0.411229952071758,
          "generator_voltage_after_v": 1.0
        },
        {
          "frequency_hz": 1900.0,
          "enabled": true,
          "target_amp_v": 0.25,
          "target_amp_uv": 250000.0,
          "tolerance": 0.0,
          "tolerance_percent": 0.0,
          "target_reached": false,
          "steps_count": 8,
          "amplitude_before_v": 0.25571455181087055,
          "amplitude_before_uv": 255714.55181087056,
          "amplitude_after_v": 0.24726767189659876,
          "amplitude_after_uv": 247267.67189659877,
          "relative_error_before": -0.022858207243482198,
          "relative_error_after": 0.010929312413604952,
          "generator_voltage_before_v": 1.0,
          "generator_voltage_after_v": 1.0
        },
        {
          "frequency_hz": 1950.0,
          "enabled": true,
          "target_amp_v": 0.25,
          "target_amp_uv": 250000.0,
          "tolerance": 0.0,
          "tolerance_percent": 0.0,
          "target_reached": false,
          "steps_count": 14,
          "amplitude_before_v": 0.0500578864030089,
          "amplitude_before_uv": 50057.8864030089,
          "amplitude_after_v": 0.2503439057760148,
          "amplitude_after_uv": 250343.90577601478,
          "relative_error_before": 0.7997684543879644,
          "relative_error_after": -0.0013756231040591427,
          "generator_voltage_before_v": 0.05,
          "generator_voltage_after_v": 0.2329708598480421
        },
        {
          "frequency_hz": 2000.0,
          "enabled": true,
          "target_amp_v": 0.25,
          "target_amp_uv": 250000.0,
          "tolerance": 0.0,
          "tolerance_percent": 0.0,
          "target_reached": false,
          "steps_count": 15,
          "amplitude_before_v": 0.21805198004118811,
          "amplitude_before_uv": 218051.9800411881,
          "amplitude_after_v": 0.25004934317591243,
          "amplitude_after_uv": 250049.34317591242,
          "relative_error_before": 0.12779207983524754,
          "relative_error_after": -0.00019737270364972304,
          "generator_voltage_before_v": 0.2329708598480421,
          "generator_voltage_after_v": 0.2688752069746069
        }
      ]
    }
  ]
}